attrtables/__init__.py
attrtables/attribute_definition.py
attrtables/attribute_value_mixin.py
attrtables/attribute_value_tables.py
attrtables-1.2.dist-info/LICENSE.txt
attrtables-1.2.dist-info/METADATA
attrtables-1.2.dist-info/WHEEL
attrtables-1.2.dist-info/top_level.txt
attrtables-1.2.dist-info/RECORD
