Metadata-Version: 2.1
Name: attrtables
Version: 1.2
Summary: Storing a dynamic set of entity attributes in a set of database tables
Home-page: https://github.com/ggonnella/attrtables
Author: Giorgio Gonnella
Author-email: gonnella@zbh.uni-hamburg.de
License: ISC
Keywords: database,attributes,entities,sqlalchemy
Classifier: Development Status :: 5 - Production/Stable
Classifier: Environment :: Console
Classifier: Intended Audience :: Developers
Classifier: Intended Audience :: End Users/Desktop
Classifier: Intended Audience :: Science/Research
Classifier: License :: OSI Approved :: ISC License (ISCL)
Classifier: Operating System :: MacOS :: MacOS X
Classifier: Operating System :: POSIX :: Linux
Classifier: Programming Language :: Python :: 3 :: Only
Classifier: Topic :: Software Development :: Libraries
License-File: LICENSE.txt
Requires-Dist: sqlalchemy
Requires-Dist: sqlalchemy-repr
